Metadata-Version: 2.4
Name: sai-pg
Version: 1.1.1
Summary: A Python Package for Statistics for Adaptive Introgression
Author-email: Xin Huang <xinhuang.res@gmail.com>
License: GPLv3
Project-URL: Homepage, https://github.com/xin-huang/sai
Classifier: License :: OSI Approved :: GNU General Public License v3 (GPLv3)
Classifier: Programming Language :: Python
Classifier: Programming Language :: Python :: 3.9
Requires-Python: ==3.9.19
License-File: LICENSE
Requires-Dist: matplotlib==3.9.1
Requires-Dist: natsort==8.4.0
Requires-Dist: numpy==1.26.4
Requires-Dist: pandas==2.2.1
Requires-Dist: pydantic==2.11.7
Requires-Dist: pysam==0.23.0
Requires-Dist: scikit-allel==1.3.7
Requires-Dist: scipy==1.12.0
Dynamic: license-file
